djson/__init__.py
djson/consts.py
djson/decoder.py
djson/encoder.py
djson/exc.py
djson/reader.py
djson/utils.py
djson-0.1.1.dist-info/DESCRIPTION.rst
djson-0.1.1.dist-info/METADATA
djson-0.1.1.dist-info/RECORD
djson-0.1.1.dist-info/WHEEL
djson-0.1.1.dist-info/metadata.json
djson-0.1.1.dist-info/top_level.txt
