Metadata-Version: 2.0
Name: djson
Version: 0.1.1
Summary: A different JSON parser for Python.
Home-page: https://github.com/damnever/djson
Author: damnever
Author-email: dxc.wolf@gmail.com
License: The BSD 3-Clause License
Keywords: djson,good,json
Platform: UNKNOWN
Classifier: Development Status :: 4 - Beta
Classifier: Intended Audience :: Developers
Classifier: Topic :: Software Development :: Libraries
Classifier: License :: OSI Approved :: BSD License
Classifier: Programming Language :: Python :: 2
Classifier: Programming Language :: Python :: 3
